README.md
setup.cfg
setup.py
deploybot/__init__.py
deploybot/deploy.py
deploybot/environment.py
deploybot/repository.py
deploybot/server.py
deploybot/user.py
deploybot_sdk.egg-info/PKG-INFO
deploybot_sdk.egg-info/SOURCES.txt
deploybot_sdk.egg-info/dependency_links.txt
deploybot_sdk.egg-info/not-zip-safe
deploybot_sdk.egg-info/requires.txt
deploybot_sdk.egg-info/top_level.txt
test/__init__.py
test/deploy_test.py
test/environment_test.py
test/repository_test.py
test/server_test.py
test/user_test.py